walter/__init__.py
walter/config.py
walter/config_test.py
walter/na.py
walter/na_test.py
walter/source_list.py
walter/source_list_test.py
walter/sources.py
walter/sources_test.py
walter-1.2.dist-info/LICENSE
walter-1.2.dist-info/WHEEL
walter-1.2.dist-info/METADATA
walter-1.2.dist-info/RECORD
