Metadata-Version: 2.1
Name: walter
Version: 1.2
Summary: A better configuration library for Django and other Python projects
Home-page: https://walter.leigh.party
License: MPL-2.0
Author: Leigh Brenecki
Author-email: leigh@brenecki.id.au
Requires-Python: >3.6
Classifier: License :: OSI Approved
Classifier: Programming Language :: Python :: 3
Classifier: Programming Language :: Python :: 3.7
Classifier: Programming Language :: Python :: 3.8
Provides-Extra: docs
Requires-Dist: appdirs
Requires-Dist: attrs
Requires-Dist: begins
Project-URL: Documentation, https://walter.leigh.party
Project-URL: Repository, https://github.com/excitedleigh/walter
